{
    "id": 1071,
    "name": "\u041a\u0430\u043c\u0435\u043d\u043d\u043e\u0435 \u043e\u0431\u043e\u0440\u0443\u0434\u043e\u0432\u0430\u043d\u0438\u0435",
    "slug": "kamennoe-oborudovanie",
    "parent": 1055,
    "description": "",
    "display": "default",
    "image": {
        "id": 22454,
        "date_created": "2024-04-07T17:31:11",
        "date_created_gmt": "2024-04-07T12:31:11",
        "date_modified": "2024-04-07T17:31:11",
        "date_modified_gmt": "2024-04-07T12:31:11",
        "src": "https://dev.smarts.uz/wp-content/uploads/2024/04/hf53ce53464c64fe1b7d7ec012141d6849.jpg_220x220.webp",
        "name": "hf53ce53464c64fe1b7d7ec012141d6849.jpg_220x220.webp",
        "alt": ""
    },
    "menu_order": 0,
    "count": 0,
    "_links": {
        "self": [
            {
                "href": "http://dev.smarts.uz/en/wp-json/wc/v3/products/categories/1071"
            }
        ],
        "collection": [
            {
                "href": "http://dev.smarts.uz/en/wp-json/wc/v3/products/categories"
            }
        ],
        "up": [
            {
                "href": "http://dev.smarts.uz/en/wp-json/wc/v3/products/categories/1055"
            }
        ]
    }
}