{
    "id": 2110,
    "name": "\u0411\u043e\u0441\u043e\u043d\u043e\u0436\u043a\u0438 \u043d\u0430 \u0442\u0430\u043d\u043a\u0435\u0442\u043a\u0435",
    "slug": "bosonozhki-na-tanketke-obuv-i-aksessuary-top-kategorii",
    "parent": 2091,
    "description": "",
    "display": "default",
    "image": {
        "id": 23544,
        "date_created": "2024-04-07T19:06:16",
        "date_created_gmt": "2024-04-07T14:06:16",
        "date_modified": "2024-04-07T19:06:16",
        "date_modified_gmt": "2024-04-07T14:06:16",
        "src": "https://dev.smarts.uz/wp-content/uploads/2024/04/ha6253d497f544a8e8b7e5dfc6f1dc6b0p.jpg_220x220-1.webp",
        "name": "ha6253d497f544a8e8b7e5dfc6f1dc6b0p.jpg_220x220-1.webp",
        "alt": ""
    },
    "menu_order": 0,
    "count": 0,
    "_links": {
        "self": [
            {
                "href": "http://dev.smarts.uz/en/wp-json/wc/v3/products/categories/2110"
            }
        ],
        "collection": [
            {
                "href": "http://dev.smarts.uz/en/wp-json/wc/v3/products/categories"
            }
        ],
        "up": [
            {
                "href": "http://dev.smarts.uz/en/wp-json/wc/v3/products/categories/2091"
            }
        ]
    }
}