{
    "id": 1676,
    "name": "\u0414\u0440\u0443\u0433\u0430\u044f \u0431\u044b\u0442\u043e\u0432\u0430\u044f \u0442\u0435\u0445\u043d\u0438\u043a\u0430",
    "slug": "drugaja-bytovaja-tehnika",
    "parent": 1659,
    "description": "",
    "display": "default",
    "image": {
        "id": 23125,
        "date_created": "2024-04-07T18:50:22",
        "date_created_gmt": "2024-04-07T13:50:22",
        "date_modified": "2024-04-07T18:50:22",
        "date_modified_gmt": "2024-04-07T13:50:22",
        "src": "https://dev.smarts.uz/wp-content/uploads/2024/04/htb1mtqpw3atbunjsszf760gfpxat.png_220x220.webp",
        "name": "htb1mtqpw3atbunjsszf760gfpxat.png_220x220.webp",
        "alt": ""
    },
    "menu_order": 0,
    "count": 0,
    "_links": {
        "self": [
            {
                "href": "http://dev.smarts.uz/en/wp-json/wc/v3/products/categories/1676"
            }
        ],
        "collection": [
            {
                "href": "http://dev.smarts.uz/en/wp-json/wc/v3/products/categories"
            }
        ],
        "up": [
            {
                "href": "http://dev.smarts.uz/en/wp-json/wc/v3/products/categories/1659"
            }
        ]
    }
}