{
    "id": 1368,
    "name": "\u0422\u043e\u043d\u0435\u0440-\u043a\u0430\u0440\u0442\u0440\u0438\u0434\u0436\u0438",
    "slug": "toner-kartridzhi",
    "parent": 1346,
    "description": "",
    "display": "default",
    "image": {
        "id": 22760,
        "date_created": "2024-04-07T17:41:48",
        "date_created_gmt": "2024-04-07T12:41:48",
        "date_modified": "2024-04-07T17:41:48",
        "date_modified_gmt": "2024-04-07T12:41:48",
        "src": "https://dev.smarts.uz/wp-content/uploads/2024/04/aa0d70ce6c1684d4e8d980f5287e2e0fdu.jpg_220x220.webp",
        "name": "aa0d70ce6c1684d4e8d980f5287e2e0fdu.jpg_220x220.webp",
        "alt": ""
    },
    "menu_order": 0,
    "count": 0,
    "_links": {
        "self": [
            {
                "href": "http://dev.smarts.uz/en/wp-json/wc/v3/products/categories/1368"
            }
        ],
        "collection": [
            {
                "href": "http://dev.smarts.uz/en/wp-json/wc/v3/products/categories"
            }
        ],
        "up": [
            {
                "href": "http://dev.smarts.uz/en/wp-json/wc/v3/products/categories/1346"
            }
        ]
    }
}