{
    "id": 2091,
    "name": "\u041e\u0431\u0443\u0432\u044c \u0438 \u0430\u043a\u0441\u0435\u0441\u0441\u0443\u0430\u0440\u044b",
    "slug": "obuv-i-aksessuary-top-kategorii",
    "parent": 1922,
    "description": "",
    "display": "default",
    "image": null,
    "menu_order": 0,
    "count": 0,
    "_links": {
        "self": [
            {
                "href": "http://dev.smarts.uz/en/wp-json/wc/v3/products/categories/2091"
            }
        ],
        "collection": [
            {
                "href": "http://dev.smarts.uz/en/wp-json/wc/v3/products/categories"
            }
        ],
        "up": [
            {
                "href": "http://dev.smarts.uz/en/wp-json/wc/v3/products/categories/1922"
            }
        ]
    }
}