{
    "id": 2189,
    "name": "\u0423\u0441\u043b\u0443\u0433\u0438 \u043f\u0435\u0448\u0435\u0433\u043e \u043a\u0443\u0440\u044c\u0435\u0440\u0430",
    "slug": "uslugi-peshego-kurera-kurerskie-uslugi-uslugi",
    "parent": 2188,
    "description": "",
    "display": "default",
    "image": null,
    "menu_order": 0,
    "count": 0,
    "_links": {
        "self": [
            {
                "href": "http://dev.smarts.uz/en/wp-json/wc/v3/products/categories/2189"
            }
        ],
        "collection": [
            {
                "href": "http://dev.smarts.uz/en/wp-json/wc/v3/products/categories"
            }
        ],
        "up": [
            {
                "href": "http://dev.smarts.uz/en/wp-json/wc/v3/products/categories/2188"
            }
        ]
    }
}